{"kill_data":{"deaths_7d":0,"mob_deaths_7d":0,"mob_kills_total":3040,"player_kdr_30d":"0","player_kills_7d":0,"player_deaths_total":0,"deaths_30d":0,"deaths_total":0,"player_kills_total":0,"mob_deaths_30d":0,"player_deaths_30d":0,"mob_kdr_30d":"3040","player_kdr_total":"0","weapon_3rd":"-","mob_kdr_7d":"3040","player_kdr_7d":"0","player_kills_30d":0,"weapon_2nd":"-","player_deaths_7d":0,"mob_deaths_total":0,"mob_kills_7d":3040,"mob_kdr_total":"3040","weapon_1st":"-","mob_kills_30d":3040},"sessions":[{"server_name":"SimplyVanillaSMP","start":"Yesterday, 21:38","length":"10m 48s","gm_series":[{"data":[["SURVIVAL",413607],["SPECTATOR",0],["CREATIVE",0],["ADVENTURE",0]],"name":"world","id":"world"},{"data":[["SURVIVAL",234544],["SPECTATOR",0],["CREATIVE",0],["ADVENTURE",0]],"name":"world_nether","id":"world_nether"}],"player_uuid":"145c5286-cd90-464a-a832-13e3f572e3a2","most_used_world":"world (63.81%)","first_session":false,"mob_kills":16,"player_url_name":"ariixxa","afk_time":"0s","name":"SimplyVanillaSMP","player_kills":[],"end":"Yesterday, 21:49","player_name":"ariixxa","world_series":[{"name":"world","y":413607,"color":"#0099C6","drilldown":"world"},{"name":"world_nether","y":234544,"color":"#66AA00","drilldown":"world_nether"}],"avg_ping":"117.4 ms","server_url_name":"SimplyVanillaSMP","server_uuid":"184915ba-208d-47f1-9bc2-b625662ffa02","deaths":0},{"server_name":"SimplyVanillaSMP","start":"Yesterday, 19:28","length":"2h 9m 20s","gm_series":[{"data":[["SURVIVAL",5618869],["SPECTATOR",0],["CREATIVE",0],["ADVENTURE",0]],"name":"world","id":"world"},{"data":[["SURVIVAL",1648811],["SPECTATOR",0],["CREATIVE",0],["ADVENTURE",0]],"name":"world_the_end","id":"world_the_end"},{"data":[["SURVIVAL",492638],["SPECTATOR",0],["CREATIVE",0],["ADVENTURE",0]],"name":"world_nether","id":"world_nether"}],"player_uuid":"145c5286-cd90-464a-a832-13e3f572e3a2","most_used_world":"world (72.41%)","first_session":false,"mob_kills":3024,"player_url_name":"ariixxa","afk_time":"7m 1s","name":"SimplyVanillaSMP","player_kills":[],"end":"Yesterday, 21:38","player_name":"ariixxa","world_series":[{"name":"world","y":5618869,"color":"#0099C6","drilldown":"world"},{"name":"world_nether","y":492638,"color":"#66AA00","drilldown":"world_nether"},{"name":"world_the_end","y":1648811,"color":"#316395","drilldown":"world_the_end"}],"avg_ping":"120.16 ms","server_url_name":"SimplyVanillaSMP","server_uuid":"184915ba-208d-47f1-9bc2-b625662ffa02","deaths":0}],"calendar_series":[{"title":"Registered: Jan 7 2022, 01:40","start":1641519636581,"color":"#8BC34A"},{"title":"Playtime: 2h 20m 8s","start":"2022-01-21","color":"#4CAF50"},{"title":"Sessions: 2","start":"2022-01-21"},{"title":"Session: 10m 48s","start":1642801092266,"end":1642801740417},{"title":"Session: 2h 9m 20s","start":1642793328753,"end":1642801089060}],"player_deaths":[],"gm_series":[{"data":[["SURVIVAL",6032476],["SPECTATOR",0],["CREATIVE",0],["ADVENTURE",0]],"name":"world","id":"world"},{"data":[["SURVIVAL",1648811],["SPECTATOR",0],["CREATIVE",0],["ADVENTURE",0]],"name":"world_the_end","id":"world_the_end"},{"data":[["SURVIVAL",727182],["SPECTATOR",0],["CREATIVE",0],["ADVENTURE",0]],"name":"world_nether","id":"world_nether"}],"world_pie_series":[{"name":"world","y":6032476,"color":"#0099C6","drilldown":"world"},{"name":"world_nether","y":727182,"color":"#66AA00","drilldown":"world_nether"},{"name":"world_the_end","y":1648811,"color":"#316395","drilldown":"world_the_end"}],"server_pie_colors":["#0099C6","#66AA00","#316395","#994499","#22AA99","#AAAA11","#6633CC","#E67300","#329262","#5574A6"],"servers":[{"server_name":"SimplyVanillaSMP","last_seen":"Yesterday, 21:49","registered":"Jan 7 2022, 01:40","gm_series":[{"data":[["SURVIVAL",6032476],["SPECTATOR",0],["CREATIVE",0],["ADVENTURE",0]],"name":"world","id":"world"},{"data":[["SURVIVAL",1648811],["SPECTATOR",0],["CREATIVE",0],["ADVENTURE",0]],"name":"world_the_end","id":"world_the_end"},{"data":[["SURVIVAL",727182],["SPECTATOR",0],["CREATIVE",0],["ADVENTURE",0]],"name":"world_nether","id":"world_nether"}],"playtime":"2h 20m 8s","session_median":"1h 10m 4s","world_pie_series":[{"name":"world","y":6032476,"color":"#0099C6","drilldown":"world"},{"name":"world_nether","y":727182,"color":"#66AA00","drilldown":"world_nether"},{"name":"world_the_end","y":1648811,"color":"#316395","drilldown":"world_the_end"}],"operator":false,"mob_kills":3040,"afk_time":"7m 1s","session_count":2,"player_kills":0,"longest_session_length":"2h 9m 20s","banned":false,"deaths":0}],"server_pie_series":[{"name":"SimplyVanillaSMP","y":8408469}],"online_activity":{"session_count_30d":2,"session_count_7d":2,"afk_time_7d":"7m 1s","mob_kill_count_30d":3040,"active_playtime_7d":"2h 13m 7s","mob_kill_count_7d":3040,"afk_time_30d":"7m 1s","average_session_length_30d":"1h 10m 4s","death_count_30d":0,"active_playtime_30d":"2h 13m 7s","average_session_length_7d":"1h 10m 4s","median_session_length_7d":"1h 10m 4s","median_session_length_30d":"1h 10m 4s","playtime_30d":"2h 20m 8s","player_kill_count_30d":0,"death_count_7d":0,"playtime_7d":"2h 20m 8s","player_kill_count_7d":0},"player_kills":[],"sessions_per_page":50,"punchcard_series":[{"x":0,"y":0,"z":0,"marker":{"radius":0}},{"x":3600000,"y":0,"z":0,"marker":{"radius":0}},{"x":7200000,"y":0,"z":0,"marker":{"radius":0}},{"x":10800000,"y":0,"z":0,"marker":{"radius":0}},{"x":14400000,"y":0,"z":0,"marker":{"radius":0}},{"x":18000000,"y":0,"z":0,"marker":{"radius":0}},{"x":21600000,"y":0,"z":0,"marker":{"radius":0}},{"x":25200000,"y":0,"z":0,"marker":{"radius":0}},{"x":28800000,"y":0,"z":0,"marker":{"radius":0}},{"x":32400000,"y":0,"z":0,"marker":{"radius":0}},{"x":36000000,"y":0,"z":0,"marker":{"radius":0}},{"x":39600000,"y":0,"z":0,"marker":{"radius":0}},{"x":43200000,"y":0,"z":0,"marker":{"radius":0}},{"x":46800000,"y":0,"z":0,"marker":{"radius":0}},{"x":50400000,"y":0,"z":0,"marker":{"radius":0}},{"x":54000000,"y":0,"z":0,"marker":{"radius":0}},{"x":57600000,"y":0,"z":0,"marker":{"radius":0}},{"x":61200000,"y":0,"z":0,"marker":{"radius":0}},{"x":64800000,"y":0,"z":0,"marker":{"radius":0}},{"x":68400000,"y":0,"z":0,"marker":{"radius":0}},{"x":72000000,"y":0,"z":0,"marker":{"radius":0}},{"x":75600000,"y":0,"z":0,"marker":{"radius":0}},{"x":79200000,"y":0,"z":0,"marker":{"radius":0}},{"x":82800000,"y":0,"z":0,"marker":{"radius":0}},{"x":0,"y":1,"z":0,"marker":{"radius":0}},{"x":3600000,"y":1,"z":0,"marker":{"radius":0}},{"x":7200000,"y":1,"z":0,"marker":{"radius":0}},{"x":10800000,"y":1,"z":0,"marker":{"radius":0}},{"x":14400000,"y":1,"z":0,"marker":{"radius":0}},{"x":18000000,"y":1,"z":0,"marker":{"radius":0}},{"x":21600000,"y":1,"z":0,"marker":{"radius":0}},{"x":25200000,"y":1,"z":0,"marker":{"radius":0}},{"x":28800000,"y":1,"z":0,"marker":{"radius":0}},{"x":32400000,"y":1,"z":0,"marker":{"radius":0}},{"x":36000000,"y":1,"z":0,"marker":{"radius":0}},{"x":39600000,"y":1,"z":0,"marker":{"radius":0}},{"x":43200000,"y":1,"z":0,"marker":{"radius":0}},{"x":46800000,"y":1,"z":0,"marker":{"radius":0}},{"x":50400000,"y":1,"z":0,"marker":{"radius":0}},{"x":54000000,"y":1,"z":0,"marker":{"radius":0}},{"x":57600000,"y":1,"z":0,"marker":{"radius":0}},{"x":61200000,"y":1,"z":0,"marker":{"radius":0}},{"x":64800000,"y":1,"z":0,"marker":{"radius":0}},{"x":68400000,"y":1,"z":0,"marker":{"radius":0}},{"x":72000000,"y":1,"z":0,"marker":{"radius":0}},{"x":75600000,"y":1,"z":0,"marker":{"radius":0}},{"x":79200000,"y":1,"z":0,"marker":{"radius":0}},{"x":82800000,"y":1,"z":0,"marker":{"radius":0}},{"x":0,"y":2,"z":0,"marker":{"radius":0}},{"x":3600000,"y":2,"z":0,"marker":{"radius":0}},{"x":7200000,"y":2,"z":0,"marker":{"radius":0}},{"x":10800000,"y":2,"z":0,"marker":{"radius":0}},{"x":14400000,"y":2,"z":0,"marker":{"radius":0}},{"x":18000000,"y":2,"z":0,"marker":{"radius":0}},{"x":21600000,"y":2,"z":0,"marker":{"radius":0}},{"x":25200000,"y":2,"z":0,"marker":{"radius":0}},{"x":28800000,"y":2,"z":0,"marker":{"radius":0}},{"x":32400000,"y":2,"z":0,"marker":{"radius":0}},{"x":36000000,"y":2,"z":0,"marker":{"radius":0}},{"x":39600000,"y":2,"z":0,"marker":{"radius":0}},{"x":43200000,"y":2,"z":0,"marker":{"radius":0}},{"x":46800000,"y":2,"z":0,"marker":{"radius":0}},{"x":50400000,"y":2,"z":0,"marker":{"radius":0}},{"x":54000000,"y":2,"z":0,"marker":{"radius":0}},{"x":57600000,"y":2,"z":0,"marker":{"radius":0}},{"x":61200000,"y":2,"z":0,"marker":{"radius":0}},{"x":64800000,"y":2,"z":0,"marker":{"radius":0}},{"x":68400000,"y":2,"z":0,"marker":{"radius":0}},{"x":72000000,"y":2,"z":0,"marker":{"radius":0}},{"x":75600000,"y":2,"z":0,"marker":{"radius":0}},{"x":79200000,"y":2,"z":0,"marker":{"radius":0}},{"x":82800000,"y":2,"z":0,"marker":{"radius":0}},{"x":0,"y":3,"z":0,"marker":{"radius":0}},{"x":3600000,"y":3,"z":0,"marker":{"radius":0}},{"x":7200000,"y":3,"z":0,"marker":{"radius":0}},{"x":10800000,"y":3,"z":0,"marker":{"radius":0}},{"x":14400000,"y":3,"z":0,"marker":{"radius":0}},{"x":18000000,"y":3,"z":0,"marker":{"radius":0}},{"x":21600000,"y":3,"z":0,"marker":{"radius":0}},{"x":25200000,"y":3,"z":0,"marker":{"radius":0}},{"x":28800000,"y":3,"z":0,"marker":{"radius":0}},{"x":32400000,"y":3,"z":0,"marker":{"radius":0}},{"x":36000000,"y":3,"z":0,"marker":{"radius":0}},{"x":39600000,"y":3,"z":0,"marker":{"radius":0}},{"x":43200000,"y":3,"z":0,"marker":{"radius":0}},{"x":46800000,"y":3,"z":0,"marker":{"radius":0}},{"x":50400000,"y":3,"z":0,"marker":{"radius":0}},{"x":54000000,"y":3,"z":0,"marker":{"radius":0}},{"x":57600000,"y":3,"z":0,"marker":{"radius":0}},{"x":61200000,"y":3,"z":0,"marker":{"radius":0}},{"x":64800000,"y":3,"z":0,"marker":{"radius":0}},{"x":68400000,"y":3,"z":0,"marker":{"radius":0}},{"x":72000000,"y":3,"z":0,"marker":{"radius":0}},{"x":75600000,"y":3,"z":0,"marker":{"radius":0}},{"x":79200000,"y":3,"z":0,"marker":{"radius":0}},{"x":82800000,"y":3,"z":0,"marker":{"radius":0}},{"x":0,"y":4,"z":0,"marker":{"radius":0}},{"x":3600000,"y":4,"z":0,"marker":{"radius":0}},{"x":7200000,"y":4,"z":0,"marker":{"radius":0}},{"x":10800000,"y":4,"z":0,"marker":{"radius":0}},{"x":14400000,"y":4,"z":0,"marker":{"radius":0}},{"x":18000000,"y":4,"z":0,"marker":{"radius":0}},{"x":21600000,"y":4,"z":0,"marker":{"radius":0}},{"x":25200000,"y":4,"z":0,"marker":{"radius":0}},{"x":28800000,"y":4,"z":0,"marker":{"radius":0}},{"x":32400000,"y":4,"z":0,"marker":{"radius":0}},{"x":36000000,"y":4,"z":0,"marker":{"radius":0}},{"x":39600000,"y":4,"z":0,"marker":{"radius":0}},{"x":43200000,"y":4,"z":0,"marker":{"radius":0}},{"x":46800000,"y":4,"z":0,"marker":{"radius":0}},{"x":50400000,"y":4,"z":0,"marker":{"radius":0}},{"x":54000000,"y":4,"z":0,"marker":{"radius":0}},{"x":57600000,"y":4,"z":0,"marker":{"radius":0}},{"x":61200000,"y":4,"z":0,"marker":{"radius":0}},{"x":64800000,"y":4,"z":0,"marker":{"radius":0}},{"x":68400000,"y":4,"z":14,"marker":{"radius":14}},{"x":72000000,"y":4,"z":0,"marker":{"radius":0}},{"x":75600000,"y":4,"z":14,"marker":{"radius":14}},{"x":79200000,"y":4,"z":0,"marker":{"radius":0}},{"x":82800000,"y":4,"z":0,"marker":{"radius":0}},{"x":0,"y":5,"z":0,"marker":{"radius":0}},{"x":3600000,"y":5,"z":0,"marker":{"radius":0}},{"x":7200000,"y":5,"z":0,"marker":{"radius":0}},{"x":10800000,"y":5,"z":0,"marker":{"radius":0}},{"x":14400000,"y":5,"z":0,"marker":{"radius":0}},{"x":18000000,"y":5,"z":0,"marker":{"radius":0}},{"x":21600000,"y":5,"z":0,"marker":{"radius":0}},{"x":25200000,"y":5,"z":0,"marker":{"radius":0}},{"x":28800000,"y":5,"z":0,"marker":{"radius":0}},{"x":32400000,"y":5,"z":0,"marker":{"radius":0}},{"x":36000000,"y":5,"z":0,"marker":{"radius":0}},{"x":39600000,"y":5,"z":0,"marker":{"radius":0}},{"x":43200000,"y":5,"z":0,"marker":{"radius":0}},{"x":46800000,"y":5,"z":0,"marker":{"radius":0}},{"x":50400000,"y":5,"z":0,"marker":{"radius":0}},{"x":54000000,"y":5,"z":0,"marker":{"radius":0}},{"x":57600000,"y":5,"z":0,"marker":{"radius":0}},{"x":61200000,"y":5,"z":0,"marker":{"radius":0}},{"x":64800000,"y":5,"z":0,"marker":{"radius":0}},{"x":68400000,"y":5,"z":0,"marker":{"radius":0}},{"x":72000000,"y":5,"z":0,"marker":{"radius":0}},{"x":75600000,"y":5,"z":0,"marker":{"radius":0}},{"x":79200000,"y":5,"z":0,"marker":{"radius":0}},{"x":82800000,"y":5,"z":0,"marker":{"radius":0}},{"x":0,"y":6,"z":0,"marker":{"radius":0}},{"x":3600000,"y":6,"z":0,"marker":{"radius":0}},{"x":7200000,"y":6,"z":0,"marker":{"radius":0}},{"x":10800000,"y":6,"z":0,"marker":{"radius":0}},{"x":14400000,"y":6,"z":0,"marker":{"radius":0}},{"x":18000000,"y":6,"z":0,"marker":{"radius":0}},{"x":21600000,"y":6,"z":0,"marker":{"radius":0}},{"x":25200000,"y":6,"z":0,"marker":{"radius":0}},{"x":28800000,"y":6,"z":0,"marker":{"radius":0}},{"x":32400000,"y":6,"z":0,"marker":{"radius":0}},{"x":36000000,"y":6,"z":0,"marker":{"radius":0}},{"x":39600000,"y":6,"z":0,"marker":{"radius":0}},{"x":43200000,"y":6,"z":0,"marker":{"radius":0}},{"x":46800000,"y":6,"z":0,"marker":{"radius":0}},{"x":50400000,"y":6,"z":0,"marker":{"radius":0}},{"x":54000000,"y":6,"z":0,"marker":{"radius":0}},{"x":57600000,"y":6,"z":0,"marker":{"radius":0}},{"x":61200000,"y":6,"z":0,"marker":{"radius":0}},{"x":64800000,"y":6,"z":0,"marker":{"radius":0}},{"x":68400000,"y":6,"z":0,"marker":{"radius":0}},{"x":72000000,"y":6,"z":0,"marker":{"radius":0}},{"x":75600000,"y":6,"z":0,"marker":{"radius":0}},{"x":79200000,"y":6,"z":0,"marker":{"radius":0}},{"x":82800000,"y":6,"z":0,"marker":{"radius":0}}],"nicknames":[{"nickname":"ariixxa","server":"SimplyVanillaSMP","date":"Yesterday, 19:28"}],"connections":[],"info":{"kick_count":0,"last_seen":"Yesterday, 21:49","favorite_server":"SimplyVanillaSMP","mob_kill_count":3040,"player_kill_count":0,"registered":"Jan 7 2022, 01:40","activity_index_group":"Irregular","playtime":"2h 20m 8s","session_median":"1h 10m 4s","active_playtime":"2h 13m 7s","operator":false,"afk_time":"7m 1s","death_count":0,"worst_ping":"362 ms","session_count":2,"online":false,"longest_session_length":"2h 9m 20s","best_ping":"49 ms","banned":false,"activity_index":"1.46","average_ping":"119.96 ms"},"first_day":1}